{
  "updated_at_utc": "2026-04-23T00:37:43Z",
  "topic": "diplomacy",
  "count": 13,
  "articles": [
    {
      "id": "35bb815c7ba2708ec0f59008659a454e7e9464f7",
      "fingerprint": "af531c1a1e187400cb43842d5776226d1a2253fc",
      "source": "TASS (RU)",
      "url": "https://tass.ru/politika/27192811",
      "published_utc": "2026-04-22T22:19:49Z",
      "title_en": "Russian Foreign Ministry: Russia was invited to participate at the highest level in the G20 summit in the USA",
      "lead_en": "Information about who will represent Moscow will appear closer to the date of the event, said Deputy Head of the Russian Diplomatic Ministry Alexander Pankin",
      "title_raw": "МИД РФ: Россию пригласили участвовать на высшем уровне в саммите G20 в США",
      "lead_raw": "Информация о том, кто будет представлять Москву, появится ближе к дате проведения мероприятия, сообщил замглавы российского дипведомства Александр Панкин",
      "topic_scores": {
        "diplomacy": 2,
        "military": 0,
        "energy": 0,
        "economy": 0,
        "local_events": 0
      },
      "topics": [
        "diplomacy"
      ],
      "primary_topic": "diplomacy"
    },
    {
      "id": "d2b443b23fec168e73921c9535720d40f806d9b2",
      "fingerprint": "1b389f1fde4a393c7c8fcbcd2c3dcf674c21d38f",
      "source": "TASS (RU)",
      "url": "https://tass.ru/politika/27192793",
      "published_utc": "2026-04-22T22:19:38Z",
      "title_en": "MFA: Russia will resume contributions to the Arctic Council after its work is restored",
      "lead_en": "Director of the Department of European Problems of the Russian Foreign Ministry Vladislav Maslennikov noted that Russia is not abandoning its financial obligations",
      "title_raw": "МИД: РФ возобновит взносы в Арктический совет после восстановления его работы",
      "lead_raw": "Директор департамента европейских проблем российского внешнеполитического ведомства Владислав Масленников отметил, что Россия не отказываемся от своих финансовых обязательств",
      "topic_scores": {
        "diplomacy": 1,
        "military": 0,
        "energy": 0,
        "economy": 0,
        "local_events": 0
      },
      "topics": [
        "diplomacy"
      ],
      "primary_topic": "diplomacy"
    },
    {
      "id": "126c7a9a0a0059a9259f975746819d8d24d13afa",
      "fingerprint": "e612b92688bd4637c3c67ff3e3d8faa7b0256e6a",
      "source": "TASS (RU)",
      "url": "https://tass.ru/politika/27192743",
      "published_utc": "2026-04-22T22:01:46Z",
      "title_en": "Russian Foreign Ministry: the situation in the Strait of Hormuz and the blockade of Iran also affect Russia",
      "lead_en": "As the deputy head of the Russian diplomatic service, Alexander Pankin, explained, due to high prices, demand decreases, the cost of fuel, fertilizers and “many other things” increases.",
      "title_raw": "МИД РФ: ситуация в Ормузском проливе и блокада Ирана влияют и на Россию",
      "lead_raw": "Как пояснил замглавы российского дипведомства Александр Панкин, из-за высоких цен снижается спрос, повышается стоимость топлива, удобрений и \"многих других вещей\"",
      "topic_scores": {
        "diplomacy": 1,
        "military": 0,
        "energy": 1,
        "economy": 0,
        "local_events": 0
      },
      "topics": [
        "diplomacy",
        "energy"
      ],
      "primary_topic": "diplomacy"
    },
    {
      "id": "10b922bf14b2e92c81d3625dc5db82987a4bea33",
      "fingerprint": "2ac5a54232356ca81ee152b7dbcde33a9905539a",
      "source": "TASS (RU)",
      "url": "https://tass.ru/politika/27192701",
      "published_utc": "2026-04-22T21:55:02Z",
      "title_en": "The Russian Foreign Ministry called unpredictability the biggest problem in relations with the United States",
      "lead_en": "Russian Deputy Foreign Minister Alexander Pankin stressed that relations between Moscow and Washington “are at their lowest point”",
      "title_raw": "В МИД РФ назвали непредсказуемость наибольшей проблемой в отношениях с США",
      "lead_raw": "Заместитель министра иностранных дел России Александр Панкин подчеркнул, что отношения между Москвой и Вашингтоном \"находятся в низшей точке\"",
      "topic_scores": {
        "diplomacy": 1,
        "military": 0,
        "energy": 0,
        "economy": 0,
        "local_events": 0
      },
      "topics": [
        "diplomacy"
      ],
      "primary_topic": "diplomacy"
    },
    {
      "id": "75cdcc91c68a3a788ace9925571350beb6b36c20",
      "fingerprint": "3aff9fcf469ca1ad113460637e6a2ee4953ad63f",
      "source": "TASS (RU)",
      "url": "https://tass.ru/politika/27192665",
      "published_utc": "2026-04-22T21:46:09Z",
      "title_en": "Russian Foreign Ministry: Russia always assumes the worst-case scenario for US sanctions",
      "lead_en": "Deputy Head of the Ministry of Foreign Affairs Alexander Pankin thus commented on Washington’s suspension of restrictions against Russian oil",
      "title_raw": "МИД РФ: Россия всегда исходит из худшего сценария по санкциям США",
      "lead_raw": "Замглавы министерства иностранных дел Александр Панкин таким образом прокомментировал приостановку Вашингтоном рестрикций против российской нефти",
      "topic_scores": {
        "diplomacy": 1,
        "military": 0,
        "energy": 1,
        "economy": 1,
        "local_events": 0
      },
      "topics": [
        "diplomacy",
        "energy"
      ],
      "primary_topic": "diplomacy"
    },
    {
      "id": "20579e6b853f3d6b1a2195341780b3f331697e60",
      "fingerprint": "62392d02be052e0250f35c92850ddebb13b46e8e",
      "source": "TASS (RU)",
      "url": "https://tass.ru/politika/27192623",
      "published_utc": "2026-04-22T21:26:26Z",
      "title_en": "Russian Foreign Ministry: the new government of Venezuela does not discriminate against Russia",
      "lead_en": "Deputy Foreign Minister Alexander Pankin noted that Moscow fully recognizes and respects the authorities of the republic",
      "title_raw": "МИД РФ: новое правительство Венесуэлы не дискриминирует Россию",
      "lead_raw": "Замминистра иностранных дел Александр Панкин отметил, что Москва полностью признает и уважает власти республики",
      "topic_scores": {
        "diplomacy": 1,
        "military": 0,
        "energy": 0,
        "economy": 0,
        "local_events": 0
      },
      "topics": [
        "diplomacy"
      ],
      "primary_topic": "diplomacy"
    },
    {
      "id": "79d028de2a79bd96e8f8dee67659a229e3f23147",
      "fingerprint": "53c6a974682316a2f7847ac8dd40e3da8cdbe799",
      "source": "TASS (RU)",
      "url": "https://tass.ru/politika/27192605",
      "published_utc": "2026-04-22T21:23:18Z",
      "title_en": "Foreign Ministry: Russia is ready to consider the possibility of new oil supplies to Cuba",
      "lead_en": "Deputy Foreign Minister of the Russian Federation Alexander Pankin added that Moscow may consider other measures to support the republic",
      "title_raw": "МИД: Россия готова рассмотреть возможность новых поставок нефти на Кубу",
      "lead_raw": "Замминистра иностранных дел РФ Александр Панкин добавил, что Москва может рассмотреть и другие меры поддержки республики",
      "topic_scores": {
        "diplomacy": 1,
        "military": 0,
        "energy": 1,
        "economy": 0,
        "local_events": 0
      },
      "topics": [
        "diplomacy",
        "energy"
      ],
      "primary_topic": "diplomacy"
    },
    {
      "id": "42ac38db656dade2de1cd31e5860b87e14256e5b",
      "fingerprint": "1f726f973735ccc5083dbd3627194249eb88c53a",
      "source": "TASS (RU)",
      "url": "https://tass.ru/politika/27192597",
      "published_utc": "2026-04-22T21:21:04Z",
      "title_en": "Pankin: relations between Russia and Hungary will be normal",
      "lead_en": "Budapest is quite pragmatic, it “does not close its doors,” says the Deputy Foreign Minister of the Russian Federation",
      "title_raw": "Панкин: отношения России и Венгрии будут нормальными",
      "lead_raw": "Будапешт достаточно прагматичен, он \"не закрывает двери\", считает замглавы МИД РФ",
      "topic_scores": {
        "diplomacy": 1,
        "military": 0,
        "energy": 0,
        "economy": 0,
        "local_events": 0
      },
      "topics": [
        "diplomacy"
      ],
      "primary_topic": "diplomacy"
    },
    {
      "id": "c95ca0bb6c2397032a2e6abb4d2961eb45888e0e",
      "fingerprint": "eadb170e22ebdcf8d243d98bea15daf57a82df92",
      "source": "TASS (RU)",
      "url": "https://tass.ru/mezhdunarodnaya-panorama/27192355",
      "published_utc": "2026-04-22T20:52:21Z",
      "title_en": "Armenia stated that it will not become a springboard for anti-Russian sentiments",
      "lead_en": "Deputy Foreign Minister of the Republic Vahan Kostanyan spoke about this on the eve of the summit of the European Political Community",
      "title_raw": "Армения заявила, что не станет плацдармом для антироссийских настроений",
      "lead_raw": "Замглавы МИД республики Ваан Костанян высказался об этом в преддверии саммита Европейского политического сообщества",
      "topic_scores": {
        "diplomacy": 2,
        "military": 0,
        "energy": 0,
        "economy": 0,
        "local_events": 0
      },
      "topics": [
        "diplomacy"
      ],
      "primary_topic": "diplomacy"
    },
    {
      "id": "7ed7d84a1394040d79e23129941b7714b6c4a722",
      "fingerprint": "e92ce8098a955181f050acd86afa654d9a00d65a",
      "source": "Meduza (EN)",
      "url": "https://meduza.io/en/news/2026/04/22/italian-pm-responds-to-russian-propagandist-solovyov-s-fascist-creature-insult-russia-s-ambassador-summoned",
      "published_utc": "2026-04-22T11:30:52Z",
      "title_en": "Italian PM responds to Russian propagandist Solovyov’s ‘fascist creature’ insult; Russia’s ambassador summoned",
      "lead_en": "Italian Prime Minister Giorgia Meloni has fired back at Russian propagandist Vladimir Solovyov after he called her a “fascist creature” on his “Solovev Live” channel and said that betrayal is her middle name — she betrayed Trump, to whom she had previously pledged her loyalty.",
      "title_raw": "Italian PM responds to Russian propagandist Solovyov’s ‘fascist creature’ insult; Russia’s ambassador summoned",
      "lead_raw": "Italian Prime Minister Giorgia Meloni has fired back at Russian propagandist Vladimir Solovyov after he called her a “fascist creature” on his “Solovev Live” channel and said that betrayal is her middle name — she betrayed Trump, to whom she had previously pledged her loyalty.",
      "topic_scores": {
        "diplomacy": 1,
        "military": 0,
        "energy": 0,
        "economy": 0,
        "local_events": 1
      },
      "topics": [
        "diplomacy"
      ],
      "primary_topic": "diplomacy"
    },
    {
      "id": "a6722e1395ac8c6f54b29258519d292be9693ec1",
      "fingerprint": "272c531515f976dc1666d2a59615b4ecc76ea8a9",
      "source": "The Moscow Times",
      "url": "https://www.themoscowtimes.com/2026/04/22/italy-summons-russian-ambassador-after-solovyov-insults-meloni-a92566",
      "published_utc": "2026-04-22T09:21:00Z",
      "title_en": "Italy Summons Russian Ambassador After Solovyov Insults Meloni",
      "lead_en": "The Russian state TV presenter called Italy's prime minister a \"disgrace to the human race,\" a \"wild beast,\" a \"certified idiot\" and a \"nasty little woman.\"",
      "title_raw": "Italy Summons Russian Ambassador After Solovyov Insults Meloni",
      "lead_raw": "The Russian state TV presenter called Italy's prime minister a \"disgrace to the human race,\" a \"wild beast,\" a \"certified idiot\" and a \"nasty little woman.\"",
      "topic_scores": {
        "diplomacy": 1,
        "military": 0,
        "energy": 0,
        "economy": 0,
        "local_events": 0
      },
      "topics": [
        "diplomacy"
      ],
      "primary_topic": "diplomacy"
    },
    {
      "id": "48e4494c5b439f4eeeab912eb0a48a644c4934d8",
      "fingerprint": "1e10517e4a026520f5adbfa4c3036c9cac4faeb2",
      "source": "The Moscow Times",
      "url": "https://www.themoscowtimes.com/2026/04/22/ukraine-repairs-druzhba-pipeline-clearing-way-for-russian-oil-flows-to-europe-a92564",
      "published_utc": "2026-04-22T07:49:47Z",
      "title_en": "Ukraine Repairs Druzhba Pipeline, Clearing Way for Russian Oil Flows to Europe",
      "lead_en": "The pipeline, which carries crude to Hungary and Slovakia, has been at the center of a monthslong diplomatic standoff.",
      "title_raw": "Ukraine Repairs Druzhba Pipeline, Clearing Way for Russian Oil Flows to Europe",
      "lead_raw": "The pipeline, which carries crude to Hungary and Slovakia, has been at the center of a monthslong diplomatic standoff.",
      "topic_scores": {
        "diplomacy": 1,
        "military": 0,
        "energy": 2,
        "economy": 0,
        "local_events": 0
      },
      "topics": [
        "diplomacy",
        "energy"
      ],
      "primary_topic": "energy"
    },
    {
      "id": "bfcafae097ba412b91385d6ad9682bd6b042a410",
      "fingerprint": "3a2c23d9f021d0a507b22fa532ef3ea6427fc1b5",
      "source": "RT",
      "url": "https://www.rt.com/news/638807-russian-envoy-denounces-iran-war-crime",
      "published_utc": "2026-04-21T12:16:16Z",
      "title_en": "‘War crime’: Russian envoy denounces US-Israeli war on Iran from Tehran rubble",
      "lead_en": "Russian Ambassador to Iran Aleksey Dedov has accused US and Israel of committing war crimes in Iran Read Full Article at RT.com",
      "title_raw": "‘War crime’: Russian envoy denounces US-Israeli war on Iran from Tehran rubble",
      "lead_raw": "Russian Ambassador to Iran Aleksey Dedov has accused US and Israel of committing war crimes in Iran Read Full Article at RT.com",
      "topic_scores": {
        "diplomacy": 2,
        "military": 0,
        "energy": 0,
        "economy": 0,
        "local_events": 0
      },
      "topics": [
        "diplomacy"
      ],
      "primary_topic": "diplomacy"
    }
  ]
}